[
  {
    "ContainingType": "HospitalSystem.API.Controllers.UsersController",
    "Method": "GetAllUsersAsync",
    "RelativePath": "api/users",
    "HttpMethod": "GET",
    "IsController": true,
    "Order": 0,
    "Parameters": [],
    "ReturnTypes": [
      {
        "Type": "Microsoft.AspNetCore.Mvc.ProblemDetails",
        "MediaTypes": [
          "text/plain",
          "application/json",
          "text/json"
        ],
        "StatusCode": 404
      },
      {
        "Type": "System.Collections.Generic.IEnumerable\u00601[[HospitalSystem.DTOs.UserDto, HospitalSystem.DTOs, Version=1.0.0.0, Culture=neutral, PublicKeyToken=null]]",
        "MediaTypes": [
          "text/plain",
          "application/json",
          "text/json"
        ],
        "StatusCode": 200
      }
    ],
    "EndpointName": "GetAllUsers"
  },
  {
    "ContainingType": "HospitalSystem.API.Controllers.UsersController",
    "Method": "AddNewUserAsync",
    "RelativePath": "api/users",
    "HttpMethod": "POST",
    "IsController": true,
    "Order": 0,
    "Parameters": [
      {
        "Name": "addUserDto",
        "Type": "HospitalSystem.DTOs.AddUserDto",
        "IsRequired": true
      }
    ],
    "ReturnTypes": [
      {
        "Type": "Microsoft.AspNetCore.Mvc.ProblemDetails",
        "MediaTypes": [
          "text/plain",
          "application/json",
          "text/json"
        ],
        "StatusCode": 400
      },
      {
        "Type": "HospitalSystem.DTOs.UserDto",
        "MediaTypes": [
          "text/plain",
          "application/json",
          "text/json"
        ],
        "StatusCode": 201
      },
      {
        "Type": "System.Void",
        "MediaTypes": [],
        "StatusCode": 500
      }
    ],
    "EndpointName": "AddNewUser"
  },
  {
    "ContainingType": "HospitalSystem.API.Controllers.UsersController",
    "Method": "UpdateUserAsync",
    "RelativePath": "api/users",
    "HttpMethod": "PUT",
    "IsController": true,
    "Order": 0,
    "Parameters": [
      {
        "Name": "updateUserDto",
        "Type": "HospitalSystem.DTOs.UpdateUserDto",
        "IsRequired": true
      }
    ],
    "ReturnTypes": [
      {
        "Type": "Microsoft.AspNetCore.Mvc.ProblemDetails",
        "MediaTypes": [
          "text/plain",
          "application/json",
          "text/json"
        ],
        "StatusCode": 400
      },
      {
        "Type": "Microsoft.AspNetCore.Mvc.ProblemDetails",
        "MediaTypes": [
          "text/plain",
          "application/json",
          "text/json"
        ],
        "StatusCode": 404
      },
      {
        "Type": "System.Void",
        "MediaTypes": [],
        "StatusCode": 500
      },
      {
        "Type": "System.Boolean",
        "MediaTypes": [
          "text/plain",
          "application/json",
          "text/json"
        ],
        "StatusCode": 200
      }
    ],
    "EndpointName": "UpdateUser"
  },
  {
    "ContainingType": "HospitalSystem.API.Controllers.UsersController",
    "Method": "FindAsync",
    "RelativePath": "api/users/{UserId}",
    "HttpMethod": "GET",
    "IsController": true,
    "Order": 0,
    "Parameters": [
      {
        "Name": "UserId",
        "Type": "System.Int32",
        "IsRequired": true
      }
    ],
    "ReturnTypes": [
      {
        "Type": "Microsoft.AspNetCore.Mvc.ProblemDetails",
        "MediaTypes": [
          "text/plain",
          "application/json",
          "text/json"
        ],
        "StatusCode": 400
      },
      {
        "Type": "Microsoft.AspNetCore.Mvc.ProblemDetails",
        "MediaTypes": [
          "text/plain",
          "application/json",
          "text/json"
        ],
        "StatusCode": 404
      },
      {
        "Type": "HospitalSystem.DTOs.UserDto",
        "MediaTypes": [
          "text/plain",
          "application/json",
          "text/json"
        ],
        "StatusCode": 200
      }
    ],
    "EndpointName": "FindUserById"
  },
  {
    "ContainingType": "HospitalSystem.API.Controllers.UsersController",
    "Method": "DeleteUserAsync",
    "RelativePath": "api/users/{UserId}",
    "HttpMethod": "DELETE",
    "IsController": true,
    "Order": 0,
    "Parameters": [
      {
        "Name": "UserId",
        "Type": "System.Int32",
        "IsRequired": true
      }
    ],
    "ReturnTypes": [
      {
        "Type": "Microsoft.AspNetCore.Mvc.ProblemDetails",
        "MediaTypes": [
          "text/plain",
          "application/json",
          "text/json"
        ],
        "StatusCode": 400
      },
      {
        "Type": "Microsoft.AspNetCore.Mvc.ProblemDetails",
        "MediaTypes": [
          "text/plain",
          "application/json",
          "text/json"
        ],
        "StatusCode": 404
      },
      {
        "Type": "System.Boolean",
        "MediaTypes": [
          "text/plain",
          "application/json",
          "text/json"
        ],
        "StatusCode": 200
      },
      {
        "Type": "System.Void",
        "MediaTypes": [],
        "StatusCode": 500
      }
    ],
    "EndpointName": "DeleteUser"
  },
  {
    "ContainingType": "HospitalSystem.API.Controllers.UsersController",
    "Method": "AddAsCurrentUserAsync",
    "RelativePath": "api/users/addAsCurrentUser/{UserId}",
    "HttpMethod": "GET",
    "IsController": true,
    "Order": 0,
    "Parameters": [
      {
        "Name": "UserId",
        "Type": "System.Int32",
        "IsRequired": true
      }
    ],
    "ReturnTypes": [
      {
        "Type": "Microsoft.AspNetCore.Mvc.ProblemDetails",
        "MediaTypes": [
          "text/plain",
          "application/json",
          "text/json"
        ],
        "StatusCode": 400
      },
      {
        "Type": "Microsoft.AspNetCore.Mvc.ProblemDetails",
        "MediaTypes": [
          "text/plain",
          "application/json",
          "text/json"
        ],
        "StatusCode": 404
      },
      {
        "Type": "System.Void",
        "MediaTypes": [],
        "StatusCode": 500
      },
      {
        "Type": "System.Boolean",
        "MediaTypes": [
          "text/plain",
          "application/json",
          "text/json"
        ],
        "StatusCode": 200
      }
    ],
    "EndpointName": "AddAsCurrentUser"
  },
  {
    "ContainingType": "HospitalSystem.API.Controllers.UsersController",
    "Method": "ChangePasswordAsync",
    "RelativePath": "api/users/changePassword",
    "HttpMethod": "PATCH",
    "IsController": true,
    "Order": 0,
    "Parameters": [
      {
        "Name": "changePasswordDto",
        "Type": "HospitalSystem.DTOs.ChangePasswordDto",
        "IsRequired": true
      }
    ],
    "ReturnTypes": [
      {
        "Type": "Microsoft.AspNetCore.Mvc.ProblemDetails",
        "MediaTypes": [
          "text/plain",
          "application/json",
          "text/json"
        ],
        "StatusCode": 400
      },
      {
        "Type": "Microsoft.AspNetCore.Mvc.ProblemDetails",
        "MediaTypes": [
          "text/plain",
          "application/json",
          "text/json"
        ],
        "StatusCode": 404
      },
      {
        "Type": "System.Void",
        "MediaTypes": [],
        "StatusCode": 500
      },
      {
        "Type": "System.Boolean",
        "MediaTypes": [
          "text/plain",
          "application/json",
          "text/json"
        ],
        "StatusCode": 200
      }
    ],
    "EndpointName": "changePassword"
  },
  {
    "ContainingType": "HospitalSystem.API.Controllers.UsersController",
    "Method": "GetUsersCountAsync",
    "RelativePath": "api/users/count",
    "HttpMethod": "GET",
    "IsController": true,
    "Order": 0,
    "Parameters": [],
    "ReturnTypes": [
      {
        "Type": "System.Int32",
        "MediaTypes": [
          "text/plain",
          "application/json",
          "text/json"
        ],
        "StatusCode": 200
      },
      {
        "Type": "System.Void",
        "MediaTypes": [],
        "StatusCode": 500
      }
    ],
    "EndpointName": "GetUsersCount"
  },
  {
    "ContainingType": "HospitalSystem.API.Controllers.UsersController",
    "Method": "FindAsync",
    "RelativePath": "api/users/find",
    "HttpMethod": "POST",
    "IsController": true,
    "Order": 0,
    "Parameters": [
      {
        "Name": "findUserDto",
        "Type": "HospitalSystem.DTOs.FindUserDto",
        "IsRequired": true
      }
    ],
    "ReturnTypes": [
      {
        "Type": "Microsoft.AspNetCore.Mvc.ProblemDetails",
        "MediaTypes": [
          "text/plain",
          "application/json",
          "text/json"
        ],
        "StatusCode": 400
      },
      {
        "Type": "Microsoft.AspNetCore.Mvc.ProblemDetails",
        "MediaTypes": [
          "text/plain",
          "application/json",
          "text/json"
        ],
        "StatusCode": 404
      },
      {
        "Type": "HospitalSystem.DTOs.UserDto",
        "MediaTypes": [
          "text/plain",
          "application/json",
          "text/json"
        ],
        "StatusCode": 200
      }
    ],
    "EndpointName": "FindUserByCredentials"
  },
  {
    "ContainingType": "HospitalSystem.API.Controllers.UsersController",
    "Method": "IsUsernameUsedAsync",
    "RelativePath": "api/users/isUsernameUsed/{Username}",
    "HttpMethod": "GET",
    "IsController": true,
    "Order": 0,
    "Parameters": [
      {
        "Name": "Username",
        "Type": "System.String",
        "IsRequired": true
      }
    ],
    "ReturnTypes": [
      {
        "Type": "Microsoft.AspNetCore.Mvc.ProblemDetails",
        "MediaTypes": [
          "text/plain",
          "application/json",
          "text/json"
        ],
        "StatusCode": 400
      },
      {
        "Type": "System.Boolean",
        "MediaTypes": [
          "text/plain",
          "application/json",
          "text/json"
        ],
        "StatusCode": 200
      }
    ],
    "EndpointName": "IsUsernameUsed"
  },
  {
    "ContainingType": "HospitalSystem.API.Controllers.UsersController",
    "Method": "UpdateUserLastLoginDateAsync",
    "RelativePath": "api/users/updateLastLoginDate/{UserId}",
    "HttpMethod": "PATCH",
    "IsController": true,
    "Order": 0,
    "Parameters": [
      {
        "Name": "UserId",
        "Type": "System.Int32",
        "IsRequired": true
      }
    ],
    "ReturnTypes": [
      {
        "Type": "Microsoft.AspNetCore.Mvc.ProblemDetails",
        "MediaTypes": [
          "text/plain",
          "application/json",
          "text/json"
        ],
        "StatusCode": 400
      },
      {
        "Type": "Microsoft.AspNetCore.Mvc.ProblemDetails",
        "MediaTypes": [
          "text/plain",
          "application/json",
          "text/json"
        ],
        "StatusCode": 404
      },
      {
        "Type": "System.Void",
        "MediaTypes": [],
        "StatusCode": 500
      },
      {
        "Type": "System.Boolean",
        "MediaTypes": [
          "text/plain",
          "application/json",
          "text/json"
        ],
        "StatusCode": 200
      }
    ],
    "EndpointName": "UpdateUserLastLoginDate"
  }
]